{
  "mahalleler": {
    "Karşıyaka": [
      "Aksoy",
      "Alaybey",
      "Atakent",
      "Bahariye",
      "Bahçelievler",
      "Bostanlı",
      "Bozköy",
      "Cumhuriyet",
      "Dedebaşı",
      "Demirköprü",
      "Donanmacı",
      "Fikri Altay",
      "Goncalar",
      "İmbatlı",
      "İnönü",
      "Latife Hanım",
      "Mavişehir",
      "Mustafa Kemal",
      "Nergiz",
      "Örnekköy",
      "Sancaklı",
      "Şemikler",
      "Tersane",
      "Tuna",
      "Yalı",
      "Yamanlar",
      "Zübeyde Hanım"
    ]
  },
  "sokaklar": {
    "Aksoy": ["1735. Sokak", "1738. Sokak", "Girne Bulvarı", "1741. Sokak", "1742. Sokak"],
    "Alaybey": ["1671 Sokak", "1675 Sokak", "Tersane Cafe Arkası Sokak", "Cemal Gürsel Caddesi"],
    "Atakent": ["Caher Dudayev Bulvarı", "2038. Sokak", "Hasan Ali Yücel Bulvarı", "2040. Sokak"],
    "Bahariye": ["Zübeyde Hanım Caddesi", "1853. Sokak", "1854. Sokak", "1860. Sokak"],
    "Bahçelievler": ["Zübeyde Hanım Caddesi", "1850. Sokak", "1831. Sokak", "Ege Caddesi"],
    "Bostanlı": ["2015. Sokak", "Şehitler Bulvarı", "Cemal Gürsel Cad.", "1809. Sokak", "Cengiz Topel Caddesi"],
    "Bozköy": ["Bozköy Yolu", "Köy İçi Yolu"],
    "Cumhuriyet": ["6651. Sokak", "6653. Sokak", "Barış Caddesi", "6655. Sokak"],
    "Dedebaşı": ["Anadolu Caddesi", "6108. Sokak", "6110. Sokak", "6112. Sokak", "Girne Bulvarı"],
    "Demirköprü": ["Bülent Ecevit Bulvarı", "6148. Sokak", "6149. Sokak", "Demirköprü Yolu"],
    "Donanmacı": ["Cemal Gürsel Caddesi", "Kemalpaşa Caddesi", "1711. Sokak", "1715. Sokak", "1717. Sokak (Çarşı)"],
    "Fikri Altay": ["Ali Alp Böke Caddesi", "6164. Sokak", "6166. Sokak"],
    "Goncalar": ["6006. Sokak", "6007. Sokak", "Müjdat Gürsu Spor Tesisleri Yolu", "Anadolu Caddesi"],
    "İmbatlı": ["Eski Havaalanı Caddesi", "6080. Sokak", "1595. Sokak"],
    "İnönü": ["6732. Sokak", "6733. Sokak", "6735. Sokak"],
    "Latife Hanım": ["7400. Sokak", "7402. Sokak", "Nazım Hikmet Bulvarı"],
    "Mavişehir": ["Caher Dudayev Bulvarı", "Aziz Nesin Bulvarı", "Pamukkale Blokları Yolu", "Selçuk Blokları Yolu"],
    "Mustafa Kemal": ["6745. Sokak", "6746. Sokak", "6747. Sokak", "Mustafa Kemal Paşa Bulvarı"],
    "Nergiz": ["Girne Bulvarı", "Ali Alp Böke Caddesi", "1775. Sokak", "1776. Sokak", "1777. Sokak"],
    "Örnekköy": ["7400. Sokak", "7402. Sokak", "Yeni Girne Pazaryeri Yolu"],
    "Sancaklı": ["Sancaklı Köyü Yolu"],
    "Şemikler": ["Anadolu Caddesi", "6415. Sokak", "6418. Sokak", "Erdoğan Akkaya Sokak"],
    "Tersane": ["Cemal Gürsel Caddesi", "1675. Sokak", "1678. Sokak"],
    "Tuna": ["1710. Sokak", "1713. Sokak", "Tiyatro Sokağı", "Karşıyaka İskelesi Yolu"],
    "Yalı": ["Caher Dudayev Bulvarı", "6321. Sokak", "6323. Sokak", "Ahmet Kemal Baysak Bulvarı"],
    "Yamanlar": ["7300. Sokak", "7302. Sokak", "Kubilay Caddesi"],
    "Zübeyde Hanım": ["7442. Sokak", "7443. Sokak", "7448. Sokak", "Zübeyde Hanım Anıt Mezarı Yolu"]
  }
}
